MANIFEST.in
README.txt
setup.py
src/collective/__init__.py
src/collective.jqueryflot.egg-info/PKG-INFO
src/collective.jqueryflot.egg-info/SOURCES.txt
src/collective.jqueryflot.egg-info/dependency_links.txt
src/collective.jqueryflot.egg-info/entry_points.txt
src/collective.jqueryflot.egg-info/namespace_packages.txt
src/collective.jqueryflot.egg-info/not-zip-safe
src/collective.jqueryflot.egg-info/requires.txt
src/collective.jqueryflot.egg-info/top_level.txt
src/collective/jqueryflot/__init__.py
src/collective/jqueryflot/configure.zcml
src/collective/jqueryflot/graphs.py
src/collective/jqueryflot/jquery.flot.js
src/collective/jqueryflot/tests.py
src/collective/jqueryflot/docs/conf.py
src/collective/jqueryflot/docs/index.txt
src/collective/jqueryflot/docs/screenshots.txt
src/collective/jqueryflot/docs/usage.txt
src/collective/jqueryflot/docs/.static/logo.png
src/collective/jqueryflot/docs/.static/options.tex
src/collective/jqueryflot/docs/.static/plone.css
src/collective/jqueryflot/docs/.templates/layout.html
src/collective/jqueryflot/docs/.templates/modindex.html
src/collective/jqueryflot/docs/.templates/options.tex
src/collective/jqueryflot/docs/.templates/search.html
src/collective/jqueryflot/docs/flot/API.txt
src/collective/jqueryflot/docs/flot/README.txt
src/collective/jqueryflot/docs/flot/index.txt
src/collective/jqueryflot/profiles/default/jsregistry.xml