Metadata-Version: 1.0
Name: collective.jqueryflot
Version: 0.1
Summary: Flot JQuery implementation for Plone
Home-page: http://svn.plone.org/svn/collective/collective.jqueryflot
Author: Rok Garbas
Author-email: rok@garbas.si
License: GPL
Keywords: plone jquery flot plot graph
Platform: UNKNOWN
Classifier: Framework :: Plone
Classifier: Programming Language :: Python
Classifier: Topic :: Software Development :: Libraries :: Python Modules
